{
  "type": "forge:conditional",
  "recipes": [
    {
      "conditions": [
        {
          "modid": "byg",
          "type": "forge:mod_loaded"
        }
      ],
      "recipe": {
        "type": "minecraft:crafting_shaped",
        "pattern": [
          "###",
          " X ",
          "###"
        ],
        "key": {
          "#": {
            "item": "minecraft:stick"
          },
          "X": {
            "item": "byg:aspen_planks"
          }
        },
        "result": {
          "item": "buddycards:aspen_card_display"
        }
      }
    }
  ]
}